HISTORY.md
LICENSE
MANIFEST.in
README.md
setup.py
battenberg/__init__.py
battenberg/cli.py
battenberg/core.py
battenberg/errors.py
battenberg/temporary_worktree.py
battenberg/utils.py
battenberg.egg-info/PKG-INFO
battenberg.egg-info/SOURCES.txt
battenberg.egg-info/dependency_links.txt
battenberg.egg-info/entry_points.txt
battenberg.egg-info/not-zip-safe
battenberg.egg-info/requires.txt
battenberg.egg-info/top_level.txt
tests/__init__.py
tests/conftest.py
tests/test_cli.py
tests/test_core.py
tests/test_temporary_worktree.py
tests/test_utils.py
tests/data/testrepo.tar
tests/data/template/cookiecutter.json
tests/data/template/{{cookiecutter.question}}/.cookiecutter.json
tests/data/upgrade-template/{{cookiecutter.question}}/new.txt