Metadata-Version: 2.1
Name: battenberg
Version: 0.2.2
Summary: Providing updates to cookiecutter projects.
Home-page: https://github.com/zillow/battenberg
Author: Zillow
License: Apache Software License 2.0
Project-URL: Documentation, https://github.com/zillow/battenberg/README.md
Project-URL: Changelog, https://github.com/zillow/battenberg/HISTORY.md
Project-URL: Code, https://github.com/zillow/battenberg
Project-URL: Issue tracker, https://github.com/zillow/battenberg/issues
Keywords: battenberg
Platform: UNKNOWN
Classifier: Development Status :: 2 - Pre-Alpha
Classifier: Intended Audience :: Developers
Classifier: License :: OSI Approved :: Apache Software License
Classifier: Natural Language :: English
Classifier: Programming Language :: Python :: 3
Classifier: Programming Language :: Python :: 3.6
Classifier: Programming Language :: Python :: 3.7
Classifier: Programming Language :: Python :: 3.8
Requires-Python: >=3.6*
Provides-Extra: dev
